{
  "Id": 0,
  "Nombre": "PA\u00D1O FIJO M3 RPT CV RECTOS",
  "LineaId": 164,
  "LineaNombre": "MEDITERRANEA RPT",
  "TipoAberturaId": 1,
  "TipoAberturaNombre": "PA\u00D1O FIJO",
  "Descripcion": "PA\u00D1O FIJO M3 RPT CV RECTOS",
  "EspesorMin": 17,
  "EspesorMax": 34,
  "Orden": 0,
  "FormaCorrediza": 0,
  "HojaCentralDoble": false,
  "Perfiles": [
    {
      "Id": 0,
      "ProductoId": 0,
      "CodigoPerfil": "62700",
      "DescripcionPerfil": "MARCO PF/VR/VB/VOB M-TRES 15RPT s/U\u00D1A EXT.",
      "Cantidad": 2,
      "FormulaCantidad": "",
      "FormulaMedida": "A",
      "AnguloCorte1": 45,
      "AnguloCorte2": 45,
      "AnguloCorte": 90,
      "Orientacion": "H",
      "TipoPerfil": "RPT",
      "GalceBase": 0,
      "AjusteGalce": 0,
      "ContravidrioFijo": false,
      "EsMarcoPerimetral": false
    },
    {
      "Id": 0,
      "ProductoId": 0,
      "CodigoPerfil": "62700",
      "DescripcionPerfil": "MARCO PF/VR/VB/VOB M-TRES 15RPT s/U\u00D1A EXT.",
      "Cantidad": 2,
      "FormulaCantidad": "",
      "FormulaMedida": "H",
      "AnguloCorte1": 45,
      "AnguloCorte2": 45,
      "AnguloCorte": 90,
      "Orientacion": "V",
      "TipoPerfil": "RPT",
      "GalceBase": 0,
      "AjusteGalce": 0,
      "ContravidrioFijo": false,
      "EsMarcoPerimetral": false
    },
    {
      "Id": 0,
      "ProductoId": 0,
      "CodigoPerfil": "8780",
      "DescripcionPerfil": "CONTRAVIDRIO RECTO DE 15.2 MM",
      "Cantidad": 2,
      "FormulaCantidad": "",
      "FormulaMedida": "A-74",
      "AnguloCorte1": 45,
      "AnguloCorte2": 45,
      "AnguloCorte": 90,
      "Orientacion": "H",
      "TipoPerfil": "Contravidrio",
      "GalceBase": 0,
      "AjusteGalce": 0,
      "ContravidrioFijo": false,
      "EsMarcoPerimetral": false
    },
    {
      "Id": 0,
      "ProductoId": 0,
      "CodigoPerfil": "8780",
      "DescripcionPerfil": "CONTRAVIDRIO RECTO DE 15.2 MM",
      "Cantidad": 2,
      "FormulaCantidad": "",
      "FormulaMedida": "H-114",
      "AnguloCorte1": 45,
      "AnguloCorte2": 45,
      "AnguloCorte": 90,
      "Orientacion": "V",
      "TipoPerfil": "Contravidrio",
      "GalceBase": 0,
      "AjusteGalce": 0,
      "ContravidrioFijo": false,
      "EsMarcoPerimetral": false
    }
  ],
  "Accesorios": [
    {
      "Id": 0,
      "ProductoId": 0,
      "CodigoAccesorio": "94130",
      "DescripcionAccesorio": "ESC.MEDITERRANEA RPT E-25 MONTICELLI",
      "FormulaCantidad": "4",
      "Unidad": "UNIDAD"
    },
    {
      "Id": 0,
      "ProductoId": 0,
      "CodigoAccesorio": "80160",
      "DescripcionAccesorio": "ESC. ALIN. MEDIT. (CE-E02) (BOLSA X 100UNID)",
      "FormulaCantidad": "4",
      "Unidad": "BOLSA X 100"
    }
  ],
  "Vidrios": [
    {
      "Id": 0,
      "ProductoId": 0,
      "Cantidad": 1,
      "FormulaCantidad": "",
      "FormulaAncho": "A-90",
      "FormulaAlto": "H-90",
      "BurleteCodigo1": "",
      "BurleteCodigo2": ""
    }
  ],
  "ConfiguracionVidrio": {
    "Tipo": "ConContravidrio",
    "Reglas": [
      {
        "Id": 0,
        "ProductoId": 0,
        "EspesorMin": 4,
        "EspesorMax": 5,
        "ContravidrioCodigo": "8760",
        "ContravidrioDescripcion": "CONTRAVIDRIO RECTO DE 29MM",
        "ContravidrioAjuste": -29,
        "BurleteCodigo1": "89130",
        "BurleteCodigo2": "82200"
      },
      {
        "Id": 0,
        "ProductoId": 0,
        "EspesorMin": 6,
        "EspesorMax": 7,
        "ContravidrioCodigo": "8760",
        "ContravidrioDescripcion": "CONTRAVIDRIO RECTO DE 29MM",
        "ContravidrioAjuste": -29,
        "BurleteCodigo1": "89130",
        "BurleteCodigo2": "82100"
      },
      {
        "Id": 0,
        "ProductoId": 0,
        "EspesorMin": 8,
        "EspesorMax": 9,
        "ContravidrioCodigo": "8760",
        "ContravidrioDescripcion": "CONTRAVIDRIO RECTO DE 29MM",
        "ContravidrioAjuste": -29,
        "BurleteCodigo1": "89130",
        "BurleteCodigo2": "82090"
      },
      {
        "Id": 0,
        "ProductoId": 0,
        "EspesorMin": 10,
        "EspesorMax": 11,
        "ContravidrioCodigo": "8770",
        "ContravidrioDescripcion": "CONTRAVIDRIO RECTO DE 22MM",
        "ContravidrioAjuste": -22,
        "BurleteCodigo1": "89130",
        "BurleteCodigo2": "82100"
      },
      {
        "Id": 0,
        "ProductoId": 0,
        "EspesorMin": 12,
        "EspesorMax": 13,
        "ContravidrioCodigo": "8770",
        "ContravidrioDescripcion": "CONTRAVIDRIO RECTO DE 22MM",
        "ContravidrioAjuste": -22,
        "BurleteCodigo1": "89130",
        "BurleteCodigo2": "82090"
      },
      {
        "Id": 0,
        "ProductoId": 0,
        "EspesorMin": 17,
        "EspesorMax": 18,
        "ContravidrioCodigo": "8780",
        "ContravidrioDescripcion": "CONTRAVIDRIO RECTO DE 15.2 MM",
        "ContravidrioAjuste": -15,
        "BurleteCodigo1": "89130",
        "BurleteCodigo2": "82110"
      },
      {
        "Id": 0,
        "ProductoId": 0,
        "EspesorMin": 19,
        "EspesorMax": 20,
        "ContravidrioCodigo": "8780",
        "ContravidrioDescripcion": "CONTRAVIDRIO RECTO DE 15.2 MM",
        "ContravidrioAjuste": -15,
        "BurleteCodigo1": "89130",
        "BurleteCodigo2": "82100"
      },
      {
        "Id": 0,
        "ProductoId": 0,
        "EspesorMin": 21,
        "EspesorMax": 22,
        "ContravidrioCodigo": "8850",
        "ContravidrioDescripcion": "CONTRAVIDRIO RECTO DE 9 MM",
        "ContravidrioAjuste": -9,
        "BurleteCodigo1": "89130",
        "BurleteCodigo2": "82200"
      },
      {
        "Id": 0,
        "ProductoId": 0,
        "EspesorMin": 23,
        "EspesorMax": 24,
        "ContravidrioCodigo": "8850",
        "ContravidrioDescripcion": "CONTRAVIDRIO RECTO DE 9 MM",
        "ContravidrioAjuste": -9,
        "BurleteCodigo1": "89130",
        "BurleteCodigo2": "82110"
      },
      {
        "Id": 0,
        "ProductoId": 0,
        "EspesorMin": 25,
        "EspesorMax": 26,
        "ContravidrioCodigo": "8850",
        "ContravidrioDescripcion": "CONTRAVIDRIO RECTO DE 9 MM",
        "ContravidrioAjuste": -9,
        "BurleteCodigo1": "89130",
        "BurleteCodigo2": "82090"
      },
      {
        "Id": 0,
        "ProductoId": 0,
        "EspesorMin": 27,
        "EspesorMax": 28,
        "ContravidrioCodigo": "8870",
        "ContravidrioDescripcion": "CONTRAVIDRIO RECTO DE 6 MM",
        "ContravidrioAjuste": -6,
        "BurleteCodigo1": "89130",
        "BurleteCodigo2": "82200"
      }
    ]
  }
}