{
  "Id": 0,
  "Nombre": "PREMARCO 648 90\u00B0",
  "LineaNombre": "MEDITERRANEA",
  "Lineas": [
    "MEDITERRANEA",
    "MEDITERRANEA RPT",
    "TRADICIONAL"
  ],
  "Perfiles": [
    {
      "Id": 0,
      "CodigoPerfil": "6480",
      "DescripcionPerfil": "PREMARCO DE 55 MM",
      "Cantidad": 2,
      "Formula": "A\u002B6",
      "AnguloCorte": 45,
      "AnguloCorte1": 90,
      "AnguloCorte2": 90,
      "Orientacion": "H"
    },
    {
      "Id": 0,
      "CodigoPerfil": "6480",
      "DescripcionPerfil": "PREMARCO DE 55 MM",
      "Cantidad": 2,
      "Formula": "H\u002B6",
      "AnguloCorte": 45,
      "AnguloCorte1": 90,
      "AnguloCorte2": 90,
      "Orientacion": "V"
    }
  ],
  "Accesorios": [
    {
      "Id": 0,
      "CodigoAccesorio": "87220",
      "DescripcionAccesorio": "GRAMPA DE AMURE PRE-MARCO (S-9 O S-09)",
      "FormulaCantidad": "((A\u002BH)*2)/250",
      "Unidad": "CAJAX100"
    },
    {
      "Id": 0,
      "CodigoAccesorio": "87230",
      "DescripcionAccesorio": "ESCUADRA P/PREM 648 Y 450 CORTE RECTO (E-78) NYLON",
      "FormulaCantidad": "4",
      "Unidad": "CAJA x 50"
    }
  ]
}